housenomics/__init__.py
housenomics/account.py
housenomics/account_name.py
housenomics/application/__init__.py
housenomics/application/import_transactions.py
housenomics/application/import_transactions_test.py
housenomics/application/open_account.py
housenomics/application/open_account_test.py
housenomics/application/repositories/transactions.py
housenomics/application/views/accounts.py
housenomics/application/views/accounts_test.py
housenomics/application/views/transactions.py
housenomics/application/views/transactions_test.py
housenomics/application/views/views.py
housenomics/application/views/views_test.py
housenomics/infrastructure/gateway_cgd_file.py
housenomics/infrastructure/gateway_cgd_file_test.py
housenomics/transaction.py
housenomics/ui/typercli/__init__.py
housenomics/ui/typercli/adapters.py
housenomics/ui/typercli/main.py
housenomics-1.2.9.dist-info/LICENSE
housenomics-1.2.9.dist-info/METADATA
housenomics-1.2.9.dist-info/WHEEL
housenomics-1.2.9.dist-info/entry_points.txt
housenomics-1.2.9.dist-info/RECORD
