Metadata-Version: 2.1
Name: housenomics
Version: 1.2.9
Summary: Manage your personal finances
License: MIT
Author: Luís Miranda
Author-email: luistm@gmail.com
Requires-Python: >=3.10,<4.0
Classifier: License :: OSI Approved :: MIT License
Classifier: Programming Language :: Python :: 3
Classifier: Programming Language :: Python :: 3.10
Classifier: Programming Language :: Python :: 3.11
Requires-Dist: pendulum (>=2.1.2,<3.0.0)
Requires-Dist: rich (>=13.5.2,<14.0.0)
Requires-Dist: sqlalchemy (>=2.0.19,<3.0.0)
Requires-Dist: toml (>=0.10.2,<0.11.0)
Requires-Dist: toolcat (>=0.0.8,<0.0.9)
Requires-Dist: typer (>=0.9.0,<0.10.0)
